spader/__init__.py
spader/spader.py
spader-0.0.1.dist-info/DESCRIPTION.rst
spader-0.0.1.dist-info/METADATA
spader-0.0.1.dist-info/RECORD
spader-0.0.1.dist-info/WHEEL
spader-0.0.1.dist-info/metadata.json
spader-0.0.1.dist-info/top_level.txt
