Metadata-Version: 2.0
Name: spader
Version: 0.0.1
Summary: A Single Page Application endpoint crawler.
Home-page: https://github.com/wongherlung/spader
Author: wongherlung
Author-email: wongherlung@gmail.com
License: UNKNOWN
Platform: UNKNOWN
Classifier: Programming Language :: Python :: 2.7
Classifier: License :: OSI Approved :: MIT License
Classifier: Operating System :: OS Independent
